git_code_review.py
git_code_review-0.1.0.dist-info/LICENSE
git_code_review-0.1.0.dist-info/METADATA
git_code_review-0.1.0.dist-info/WHEEL
git_code_review-0.1.0.dist-info/entry_points.txt
git_code_review-0.1.0.dist-info/top_level.txt
git_code_review-0.1.0.dist-info/RECORD
