Metadata-Version: 2.1
Name: git-code-review
Version: 0.1.0
Summary: Git Code Review
Home-page: https://github.com/ReverentEngineer/git-code-review
Author: Jeff Caffrey-Hill
Author-email: jeff@reverentengineer.com
License: UNKNOWN
Keywords: git,code,review,cli
Platform: UNKNOWN
Classifier: Development Status :: 3 - Alpha
Classifier: Intended Audience :: Developers
Classifier: License :: OSI Approved :: Apache Software License
Classifier: Programming Language :: Python :: 2
Classifier: Programming Language :: Python :: 3
Provides-Extra: dev
Requires-Dist: pyflake8 ; extra == 'dev'
